soundsig/__init__.py
soundsig/basis.py
soundsig/check_versions.py
soundsig/coherence.py
soundsig/colormaps.py
soundsig/complex_pca.py
soundsig/detect_peaks.py
soundsig/discrete_process.py
soundsig/discriminate.py
soundsig/entropy_estimators.py
soundsig/graph_cluster.py
soundsig/hht.py
soundsig/hinton.py
soundsig/incrowd.py
soundsig/memd.py
soundsig/optimization.py
soundsig/plots.py
soundsig/quasirand.py
soundsig/signal.py
soundsig/sound.py
soundsig/spikes.py
soundsig/stats.py
soundsig/strf_bank.py
soundsig/strfs.py
soundsig/timefreq.py
soundsig-3.1.1.dist-info/licenses/LICENSE.txt
soundsig-3.1.1.dist-info/METADATA
soundsig-3.1.1.dist-info/WHEEL
soundsig-3.1.1.dist-info/top_level.txt
soundsig-3.1.1.dist-info/RECORD
