Metadata-Version: 2.4
Name: soundsig
Version: 3.1.1
Summary: Sound and Signal Analysis Tools for Bioacousticians and Auditory Neurophysiologists
Home-page: https://github.com/theunissenlab/soundsig
Author: Frederic Theunissen
Author-email: theunissen@berkeley.edu
Keywords: bioacoustics biosound vocalization auditory
Classifier: Development Status :: 4 - Beta
Classifier: Programming Language :: Python :: 3.0
License-File: LICENSE.txt
Requires-Dist: numpy
Requires-Dist: scipy
Requires-Dist: matplotlib
Requires-Dist: h5py
Requires-Dist: mne
Requires-Dist: nitime
Requires-Dist: pandas
Requires-Dist: scikit-learn
Requires-Dist: numba
Requires-Dist: librosa
Dynamic: author
Dynamic: author-email
Dynamic: classifier
Dynamic: home-page
Dynamic: keywords
Dynamic: license-file
Dynamic: requires-dist
Dynamic: summary
